receiptor/__init__.py
receiptor/constants.py
receiptor/receiptor.py
receiptor/gmail_connector/__init__.py
receiptor/gmail_connector/gmail_connector.py
receiptor/gmail_connector/gmail_message_parser.py
receiptor/gmail_connector/gmail_message_parser_with_struct_data.py
receiptor/llm_parser/__init__.py
receiptor/llm_parser/gpt_4o_mini_parser/__init__.py
receiptor/llm_parser/gpt_4o_mini_parser/custom_parser.py
receiptor/llm_parser/gpt_4o_mini_parser/gpt_4o_mini.py
receiptor/models/__init__.py
receiptor/models/attachment.py
receiptor/models/message.py
receiptor/models/message_struct_data.py
receiptor/models/ocr_text_object.py
receiptor/ocr/__init__.py
receiptor/ocr/text_extractor.py
receiptor/utils/__init__.py
receiptor/utils/helpers.py
receiptor-1.1.1.dist-info/LICENSE
receiptor-1.1.1.dist-info/METADATA
receiptor-1.1.1.dist-info/WHEEL
receiptor-1.1.1.dist-info/top_level.txt
receiptor-1.1.1.dist-info/RECORD
