Metadata-Version: 2.1
Name: receiptor
Version: 1.1.1
Summary: Extract receipt / invoice/ orders data from your gmail .
Author: Omkar Malpure
Author-email: <malpureomkar5@gmail.com>
Keywords: receipts,receipt,invoice,receipts gmail,invoice gmail,python gmail receipt,python gmail invoice,receipt gmail data,gmail receipt data,gmail invoice data,invoice gmail data,python code for extracting gmail receipt data,python code for extracting gmail invoice data,processing Gmail receipts / invoices,handling data in Python
Classifier: Development Status :: 1 - Planning
Classifier: Intended Audience :: Developers
Classifier: Programming Language :: Python :: 3
Classifier: Operating System :: Unix
Classifier: Operating System :: MacOS :: MacOS X
Classifier: Operating System :: Microsoft :: Windows
License-File: LICENSE
Requires-Dist: aiohttp==3.9.3
Requires-Dist: pycurl
Requires-Dist: aiosignal==1.3.1
Requires-Dist: annotated-types==0.6.0
Requires-Dist: anyio==4.2.0
Requires-Dist: attrs==23.2.0
Requires-Dist: beautifulsoup4==4.12.3
Requires-Dist: certifi==2024.2.2
Requires-Dist: cffi==1.16.0
Requires-Dist: charset-normalizer==3.3.2
Requires-Dist: cryptography==42.0.2
Requires-Dist: pycryptodome==3.10.1
Requires-Dist: Deprecated==1.2.14
Requires-Dist: fastapi==0.109.2
Requires-Dist: frozenlist==1.4.1
Requires-Dist: idna==3.6
Requires-Dist: jwcrypto==1.5.1
Requires-Dist: lxml==5.1.0
Requires-Dist: multidict==6.0.5
Requires-Dist: pycparser==2.21
Requires-Dist: pydantic==2.6.1
Requires-Dist: pydantic-core==2.16.2
Requires-Dist: PyJWT==2.8.0
Requires-Dist: PyPDF2==3.0.1
Requires-Dist: python-docx==1.1.0
Requires-Dist: python-jwt==4.1.0
Requires-Dist: requests==2.31.0
Requires-Dist: sniffio==1.3.0
Requires-Dist: soupsieve==2.5
Requires-Dist: typing-extensions==4.9.0
Requires-Dist: urllib3==2.2.0
Requires-Dist: wrapt==1.16.0
Requires-Dist: yarl==1.9.4
Requires-Dist: google-generativeai==0.3.2
Requires-Dist: python-dotenv==1.0.1
Requires-Dist: openai
Requires-Dist: tiktoken==0.7.0
Requires-Dist: google-play-scraper
Requires-Dist: httpx==0.26.0
Requires-Dist: pyOpenSSL==17.2.0
Requires-Dist: colorthief
